lpsolvewrapper/__init__.py
lpsolvewrapper/liblpsolve55.so
lpsolvewrapper/lpsolve55.cpython-38-x86_64-linux-gnu.so
lpsolvewrapper-1.1.0.dist-info/LICENSE.txt
lpsolvewrapper-1.1.0.dist-info/METADATA
lpsolvewrapper-1.1.0.dist-info/WHEEL
lpsolvewrapper-1.1.0.dist-info/top_level.txt
lpsolvewrapper-1.1.0.dist-info/RECORD
