Metadata-Version: 2.1
Name: lpsolvewrapper
Version: 1.1.0
Summary: Python wrapper for compiled lpsolve bindings
Home-page: https://github.com/theweiyu/lpsolvewrapper
Author: Weiyu Chen
License: UNKNOWN
Keywords: lpsolve python3 wrapper compiled
Platform: UNKNOWN
Classifier: Development Status :: 3 - Alpha
Classifier: Intended Audience :: Developers
Classifier: License :: OSI Approved :: GNU Lesser General Public License v3 (LGPLv3)
Classifier: Programming Language :: Python :: 3.6
License-File: LICENSE.txt
